TOPSIS/__init__.py
TOPSIS/topsis.py
Abhishek-1.0.1.dist-info/Licence.txt
Abhishek-1.0.1.dist-info/METADATA
Abhishek-1.0.1.dist-info/WHEEL
Abhishek-1.0.1.dist-info/entry_points.txt
Abhishek-1.0.1.dist-info/top_level.txt
Abhishek-1.0.1.dist-info/RECORD
