Metadata-Version: 2.1
Name: Abhishek
Version: 1.0.1
Summary: TOPSIS
Home-page: UNKNOWN
Author: Abhishek
License: MIT
Platform: UNKNOWN
Classifier: License :: OSI Approved :: MIT License
Classifier: Programming Language :: Python :: 3.6
Classifier: Programming Language :: Python :: 3.7
Classifier: Programming Language :: Python :: 3.8
